{"establecimientos": [{"tipologia_descripcion": "Establecimiento de salud sin internación de diagnóstico y tratamiento", "vih": false, "cp": "3240", "id": 50260212329179, "domicilio": "Avenida Rivadavia 633", "web": null, "provincia": "Chubut", "lon": -67.48355500000002, "tipologia": "ESSIDT", "nombre": "Kin Sport", "telefono": "0297-4475310", "email": "kin_sportcomodoro@hotmail.com", "financiamiento": "Publico", "departamento": "Escalante", "lat": -45.8621272, "tipologia_categoria": "Con atención médica diaria y con especialidades y/o otras profesiones", "sangre": false, "dependencia": "Privado", "zoom": 14, "tipo_telefono": "Recepción", "localidad": "Comodoro Rivadavia"}, {"tipologia_descripcion": "Establecimiento de salud sin internación de diagnóstico y tratamiento", "vih": false, "cp": "9000", "id": 50260212329186, "domicilio": "Ameghino 1311", "web": null, "provincia": "Chubut", "lon": -67.49461984625668, "tipologia": "ESSIDT", "nombre": "Odontologia Del Plata", "telefono": "0297-4064477", "email": "drsiciliano@live.com", "financiamiento": "Privado", "departamento": "Escalante", "lat": -45.863383491641954, "tipologia_categoria": "Con atención médica diaria y con especialidades y/o otras profesiones", "sangre": false, "dependencia": "Privado", "zoom": 14, "tipo_telefono": "Recepción", "localidad": "Comodoro Rivadavia  (Comodoro Rivadavia)"}]}